__init__.py
asleep/__init__.py
asleep/collate_outputs.py
asleep/get_sleep.py
asleep/macros.py
asleep/models.py
asleep/process_cap24.py
asleep/simple.py
asleep/sleep_stats.py
asleep/sleep_windows.py
asleep/sleepnet.py
asleep/sslmodel.py
asleep/summary.py
asleep/test_summary.py
asleep/train_capture24.py
asleep/utils.py
asleep/visu_sleep.py
asleep/conf/__init__.py
asleep/conf/config.yaml
asleep/conf/config_eval.yaml
asleep/conf/data/deployment.yaml
asleep/conf/model/baseline.yaml
asleep/conf/model/cnn_lstm_eval.yaml
asleep-0.4.16.dist-info/licenses/LICENSE.md
asleep-0.4.16.dist-info/METADATA
asleep-0.4.16.dist-info/WHEEL
asleep-0.4.16.dist-info/entry_points.txt
asleep-0.4.16.dist-info/top_level.txt
asleep-0.4.16.dist-info/RECORD
