Metadata-Version: 2.4
Name: asleep
Version: 0.4.16
Summary: A sleep classification tool for wearables
Author-email: Hang Yuan <angerhangy@gmail.com>
Maintainer-email: Hang Yuan <angerhangy@gmail.com>
License: # Academic Use Licence
Project-URL: Homepage, https://github.com/OxWearables/asleep
Project-URL: Bug Reports, https://github.com/OxWearables/asleep/issues
Project-URL: Source, https://github.com/OxWearables/asleep
Keywords: sleep,wearables,machine learning
Classifier: Development Status :: 3 - Alpha
Classifier: Intended Audience :: Developers
Classifier: Intended Audience :: Education
Classifier: Intended Audience :: Science/Research
Classifier: Intended Audience :: Healthcare Industry
Classifier: Topic :: Scientific/Engineering :: Artificial Intelligence
Classifier: Topic :: Scientific/Engineering :: Medical Science Apps.
Classifier: License :: OSI Approved :: MIT License
Classifier: Programming Language :: Python :: 3
Classifier: Programming Language :: Python :: 3.8
Classifier: Programming Language :: Python :: 3.9
Classifier: Programming Language :: Python :: 3 :: Only
Requires-Python: >=3.8
License-File: LICENSE.md
Requires-Dist: peppercorn
Requires-Dist: actipy
Requires-Dist: numpy
Requires-Dist: pandas
Requires-Dist: scipy
Requires-Dist: joblib
Requires-Dist: torch
Requires-Dist: torchvision
Requires-Dist: transforms3d
Requires-Dist: stepcount
Requires-Dist: hydra-core
Requires-Dist: matplotlib
Provides-Extra: dev
Requires-Dist: check-manifest; extra == "dev"
Provides-Extra: test
Requires-Dist: coverage; extra == "test"
Dynamic: license-file
